pyTrucoEngine/__init__.py
pyTrucoEngine/card.py
pyTrucoEngine/cards.py
pyTrucoEngine/player.py
pyTrucoEngine/table.py
pyTrucoEngine/team.py
pyTrucoEngine/actions/__init__.py
pyTrucoEngine/actions/action.py
pyTrucoEngine/actions/envido_actions.py
pyTrucoEngine/actions/functions.py
pyTrucoEngine/actions/initial_action.py
pyTrucoEngine/actions/jugar_carta_action.py
pyTrucoEngine/actions/truco_actions.py
pyTrucoEngine/controllers/__init__.py
pyTrucoEngine/controllers/controller.py
pyTrucoEngine/controllers/game_controller.py
pyTrucoEngine/controllers/hand_controllers.py
pyTrucoEngine/controllers/round_controller.py
pyTrucoEngine/handlers/__init__.py
pyTrucoEngine/handlers/signals.py
pyTrucoEngine/handlers/turn.py
PyTrucoEngine-1.0.1.dist-info/METADATA
PyTrucoEngine-1.0.1.dist-info/WHEEL
PyTrucoEngine-1.0.1.dist-info/top_level.txt
PyTrucoEngine-1.0.1.dist-info/RECORD
