Metadata-Version: 2.1
Name: PyTrucoEngine
Version: 1.0.1
Summary: Motor de truco argentino escrito en python
Home-page: https://softwarebrc.com.ar/
Author: Lautaro Linquiman
Author-email: lylinquiman@gmail.com
License: UNKNOWN
Project-URL: Bug Tracker, https://github.com/Ymil/libPyTruco
Platform: UNKNOWN
Classifier: Programming Language :: Python :: 3
Requires-Python: >=3.6
